webhooks/__init__.py
webhooks/decorators.py
webhooks/encoders.py
webhooks/exceptions.py
webhooks/hashes.py
webhooks/senders/__init__.py
webhooks/senders/async_redis.py
webhooks/senders/base.py
webhooks/senders/simple.py
webhooks/senders/targeted.py
webhooks-0.4.2.dist-info/DESCRIPTION.rst
webhooks-0.4.2.dist-info/METADATA
webhooks-0.4.2.dist-info/metadata.json
webhooks-0.4.2.dist-info/RECORD
webhooks-0.4.2.dist-info/top_level.txt
webhooks-0.4.2.dist-info/WHEEL
