Metadata-Version: 1.1
Name: webhooks
Version: 0.4.2
Summary: Python + Webhooks mMade Easy
Home-page: https://github.com/pydanny/webhooks
Author: Daniel Greenfeld
Author-email: pydanny@gmail.com
License: BSD
Keywords: webhooks
Platform: UNKNOWN
Classifier: Development Status :: 4 - Beta
Classifier: Intended Audience :: Developers
Classifier: License :: OSI Approved :: BSD License
Classifier: Natural Language :: English
Classifier: Programming Language :: Python :: 2.7
Classifier: Programming Language :: Python :: 3.3
Classifier: Programming Language :: Python :: 3.4
